
    {
        
            "content": [
                {
                    "html":"<h2 class='font-serif'>Let's begin</h2><p>The words you use on your buttons can make or break a customers engagement.</p><p class='font-bold'>The following are all content changes, so you can make these changes without a developer's help</p>"

                },
                {
                    "html": "<h2 class='font-serif' id='tip-1'>1. Use action words</h2><p>Use verbs like <strong>Reserve</strong>, <strong>Get</strong>, <strong>Buy</strong> and <strong>Join</strong>. These words are more engaging than generic terms like “Submit” or “Subscribe” and give the user a clearer picture of what will happen when they click the button."
                },
                {
                    "html": "<h2 class='font-serif' id='tip-2'>2. Be transparent</h2><p>Don't hide your important links within paragraphs, give them a beautiful button.</p><p>Couple your verb or action words with clear information. So instead of simply <strong>Join</strong> a better button might read <strong>Join the UX group</strong></p>"
                },
                {
                     "html": "<h2 class='font-serif' id='tip-3'>3. Create urgency</h2><p>\"Urgency\" is about being transparent (and honest) about how limiting the action is. For instance, if it's the day before an event you might use <strong>Book your spot – only 2 left</strong>"
                }
            ],
            "inspo":
            {
                "link": "https://dribbble.com/epluribusunum1985/collections/7103061-How-to-avoid-bland-buttons",
                "image": "https://via.placeholder.com/150"
            },
            "reference": [
                
                
                
            ]
        
    }
